[
	{
		"title": "Poetry and Prosody",
		"number": "603-213-DW",
		"sections": [
			{
				"title": "Poetry and Prosody",
				"number": "00001",
				"teacher": "Susan Elmslie",
				"schedule": [
					{
						"day": "Thursday",
						"begin": "10:00 AM",
						"end": "11:30 AM",
						"duration": {
							"hours": 1,
							"minutes": 30
						}
					},
					{
						"day": "Monday",
						"begin": "1:00 PM",
						"end": "2:30 PM",
						"duration": {
							"hours": 1,
							"minutes": 30
						}
					}
				]
			},
			{
				"title": "Poetry and Prosody",
				"number": "00002",
				"teacher": "David Gelineau",
				"schedule": [
					{
						"day": "Thursday",
						"begin": "2:30 PM",
						"end": "4:00 PM",
						"duration": {
							"hours": 1,
							"minutes": 30
						}
					},
					{
						"day": "Tuesday",
						"begin": "2:30 PM",
						"end": "4:00 PM",
						"duration": {
							"hours": 1,
							"minutes": 30
						}
					}
				]
			}
		]
	},
	{
		"title": "Creative Writing Workshop",
		"number": "603-413-DW",
		"sections": [
			{
				"number": "00001",
				"teacher": "Christian Charette",
				"schedule": [
					{
						"day": "Wednesday",
						"begin": "4:00 PM",
						"end": "6:00 PM",
						"duration": {
							"hours": 2,
							"minutes": 0
						}
					},
					{
						"day": "Monday",
						"begin": "4:00 PM",
						"end": "6:00 PM",
						"duration": {
							"hours": 2,
							"minutes": 0
						}
					}
				]
			},
			{
				"number": "00002",
				"teacher": "Andrea Strudensky",
				"schedule": [
					{
						"day": "Friday",
						"begin": "8:00 AM",
						"end": "10:00 AM",
						"duration": {
							"hours": 2,
							"minutes": 0
						}
					},
					{
						"day": "Tuesday",
						"begin": "8:00 AM",
						"end": "10:00 AM",
						"duration": {
							"hours": 2,
							"minutes": 0
						}
					}
				]
			}
		]
	},
	{
		"title": "Integrating Activity (IA)",
		"number": "603-498-DW",
		"sections": [
			{
				"number": "00001",
				"teacher": "Liana Bellon",
				"schedule": [
					{
						"day": "Thursday",
						"begin": "4:00 PM",
						"end": "6:00 PM",
						"duration": {
							"hours": 2,
							"minutes": 0
						}
					},
					{
						"day": "Tuesday",
						"begin": "4:00 PM",
						"end": "6:00 PM",
						"duration": {
							"hours": 2,
							"minutes": 0
						}
					}
				]
			}
		]
	},
	{
		"title": "Literary Currents",
		"number": "603-914-DW",
		"sections": [
			{
				"title": "Literary Currents",
				"number": "00001",
				"teacher": "Shalon Nicole Noble",
				"schedule": [
					{
						"day": "Friday",
						"begin": "11:30 AM",
						"end": "1:00 PM",
						"duration": {
							"hours": 1,
							"minutes": 30
						}
					},
					{
						"day": "Wednesday",
						"begin": "11:30 AM",
						"end": "1:00 PM",
						"duration": {
							"hours": 1,
							"minutes": 30
						}
					}
				]
			}
		]
	},
	{
		"title": "Literature and Creative Practice",
		"number": "603-915-DW",
		"sections": [
			{
				"number": "00001",
				"teacher": "Anna Lewton-Brain, Justin Pfefferle",
				"schedule": [
					{
						"day": "Friday",
						"begin": "10:00 AM",
						"end": "11:30 AM",
						"duration": {
							"hours": 1,
							"minutes": 30
						}
					},
					{
						"day": "Tuesday",
						"begin": "10:00 AM",
						"end": "11:30 AM",
						"duration": {
							"hours": 1,
							"minutes": 30
						}
					}
				]
			}
		]
	},
	{
		"title": "Literature and Borders",
		"number": "603-917-DW",
		"sections": [
			{
				"number": "00001",
				"teacher": "Pauline Morel",
				"schedule": [
					{
						"day": "Friday",
						"begin": "11:30 AM",
						"end": "1:00 PM",
						"duration": {
							"hours": 1,
							"minutes": 30
						}
					},
					{
						"day": "Wednesday",
						"begin": "11:30 AM",
						"end": "1:00 PM",
						"duration": {
							"hours": 1,
							"minutes": 30
						}
					}
				]
			}
		]
	}
]