[
	{
		"title": "Research Methods",
		"number": "300-300-DW",
		"sections": [
			{
				"number": "00001",
				"teacher": "Lazar Konforti",
				"schedule": [
					{
						"day": "Wednesday",
						"begin": "4:00 PM",
						"end": "6:00 PM",
						"duration": {
							"hours": 2,
							"minutes": 0
						}
					},
					{
						"day": "Monday",
						"begin": "4:00 PM",
						"end": "6:00 PM",
						"duration": {
							"hours": 2,
							"minutes": 0
						}
					}
				]
			},
			{
				"number": "00002",
				"teacher": "Lazar Konforti",
				"schedule": [
					{
						"day": "Friday",
						"begin": "10:00 AM",
						"end": "12:00 PM",
						"duration": {
							"hours": 2,
							"minutes": 0
						}
					},
					{
						"day": "Tuesday",
						"begin": "10:00 AM",
						"end": "12:00 PM",
						"duration": {
							"hours": 2,
							"minutes": 0
						}
					}
				]
			},
			{
				"number": "00003",
				"teacher": "Richard Soare",
				"schedule": [
					{
						"day": "Thursday",
						"begin": "10:00 AM",
						"end": "12:00 PM",
						"duration": {
							"hours": 2,
							"minutes": 0
						}
					},
					{
						"day": "Monday",
						"begin": "2:00 PM",
						"end": "4:00 PM",
						"duration": {
							"hours": 2,
							"minutes": 0
						}
					}
				]
			},
			{
				"number": "00004",
				"teacher": "Richard Soare",
				"schedule": [
					{
						"day": "Thursday",
						"begin": "8:00 AM",
						"end": "10:00 AM",
						"duration": {
							"hours": 2,
							"minutes": 0
						}
					},
					{
						"day": "Monday",
						"begin": "12:00 PM",
						"end": "2:00 PM",
						"duration": {
							"hours": 2,
							"minutes": 0
						}
					}
				]
			},
			{
				"number": "00005",
				"teacher": "Nadia Vracotas",
				"schedule": [
					{
						"day": "Friday",
						"begin": "12:00 PM",
						"end": "2:00 PM",
						"duration": {
							"hours": 2,
							"minutes": 0
						}
					},
					{
						"day": "Wednesday",
						"begin": "12:00 PM",
						"end": "2:00 PM",
						"duration": {
							"hours": 2,
							"minutes": 0
						}
					}
				]
			},
			{
				"number": "00006",
				"teacher": "Nadia Vracotas",
				"schedule": [
					{
						"day": "Wednesday",
						"begin": "10:00 AM",
						"end": "12:00 PM",
						"duration": {
							"hours": 2,
							"minutes": 0
						}
					},
					{
						"day": "Monday",
						"begin": "10:00 AM",
						"end": "12:00 PM",
						"duration": {
							"hours": 2,
							"minutes": 0
						}
					}
				]
			},
			{
				"number": "00007",
				"teacher": "Anick Legault",
				"schedule": [
					{
						"day": "Friday",
						"begin": "12:00 PM",
						"end": "2:00 PM",
						"duration": {
							"hours": 2,
							"minutes": 0
						}
					},
					{
						"day": "Wednesday",
						"begin": "12:00 PM",
						"end": "2:00 PM",
						"duration": {
							"hours": 2,
							"minutes": 0
						}
					}
				]
			},
			{
				"number": "00008",
				"teacher": "Anick Legault",
				"schedule": [
					{
						"day": "Thursday",
						"begin": "12:00 PM",
						"end": "2:00 PM",
						"duration": {
							"hours": 2,
							"minutes": 0
						}
					},
					{
						"day": "Tuesday",
						"begin": "12:00 PM",
						"end": "2:00 PM",
						"duration": {
							"hours": 2,
							"minutes": 0
						}
					}
				]
			},
			{
				"number": "00009",
				"teacher": "Carolina Pineda",
				"schedule": [
					{
						"day": "Friday",
						"begin": "10:00 AM",
						"end": "12:00 PM",
						"duration": {
							"hours": 2,
							"minutes": 0
						}
					},
					{
						"day": "Tuesday",
						"begin": "10:00 AM",
						"end": "12:00 PM",
						"duration": {
							"hours": 2,
							"minutes": 0
						}
					}
				]
			},
			{
				"number": "00010",
				"teacher": "Carolina Pineda",
				"schedule": [
					{
						"day": "Thursday",
						"begin": "4:00 PM",
						"end": "6:00 PM",
						"duration": {
							"hours": 2,
							"minutes": 0
						}
					},
					{
						"day": "Tuesday",
						"begin": "4:00 PM",
						"end": "6:00 PM",
						"duration": {
							"hours": 2,
							"minutes": 0
						}
					}
				]
			},
			{
				"number": "00011",
				"teacher": "Verity Whalen",
				"schedule": [
					{
						"day": "Thursday",
						"begin": "12:00 PM",
						"end": "2:00 PM",
						"duration": {
							"hours": 2,
							"minutes": 0
						}
					},
					{
						"day": "Tuesday",
						"begin": "12:00 PM",
						"end": "2:00 PM",
						"duration": {
							"hours": 2,
							"minutes": 0
						}
					}
				]
			},
			{
				"number": "00012",
				"teacher": "Verity Whalen",
				"schedule": [
					{
						"day": "Thursday",
						"begin": "8:00 AM",
						"end": "10:00 AM",
						"duration": {
							"hours": 2,
							"minutes": 0
						}
					},
					{
						"day": "Monday",
						"begin": "12:00 PM",
						"end": "2:00 PM",
						"duration": {
							"hours": 2,
							"minutes": 0
						}
					}
				]
			},
			{
				"number": "00013",
				"teacher": "Verity Whalen",
				"schedule": [
					{
						"day": "Wednesday",
						"begin": "10:00 AM",
						"end": "12:00 PM",
						"duration": {
							"hours": 2,
							"minutes": 0
						}
					},
					{
						"day": "Monday",
						"begin": "10:00 AM",
						"end": "12:00 PM",
						"duration": {
							"hours": 2,
							"minutes": 0
						}
					}
				]
			},
			{
				"number": "00014",
				"teacher": "Dan Loomer",
				"schedule": [
					{
						"day": "Friday",
						"begin": "12:00 PM",
						"end": "2:00 PM",
						"duration": {
							"hours": 2,
							"minutes": 0
						}
					},
					{
						"day": "Wednesday",
						"begin": "12:00 PM",
						"end": "2:00 PM",
						"duration": {
							"hours": 2,
							"minutes": 0
						}
					}
				]
			},
			{
				"number": "00015",
				"teacher": "Dan Loomer",
				"schedule": [
					{
						"day": "Thursday",
						"begin": "8:00 AM",
						"end": "10:00 AM",
						"duration": {
							"hours": 2,
							"minutes": 0
						}
					},
					{
						"day": "Monday",
						"begin": "12:00 PM",
						"end": "2:00 PM",
						"duration": {
							"hours": 2,
							"minutes": 0
						}
					}
				]
			},
			{
				"number": "00016",
				"teacher": "Rubens Lima Moraes",
				"schedule": [
					{
						"day": "Thursday",
						"begin": "10:00 AM",
						"end": "12:00 PM",
						"duration": {
							"hours": 2,
							"minutes": 0
						}
					},
					{
						"day": "Monday",
						"begin": "2:00 PM",
						"end": "4:00 PM",
						"duration": {
							"hours": 2,
							"minutes": 0
						}
					}
				]
			},
			{
				"number": "00017",
				"teacher": "Francine Small",
				"schedule": [
					{
						"day": "Wednesday",
						"begin": "4:00 PM",
						"end": "6:00 PM",
						"duration": {
							"hours": 2,
							"minutes": 0
						}
					},
					{
						"day": "Monday",
						"begin": "4:00 PM",
						"end": "6:00 PM",
						"duration": {
							"hours": 2,
							"minutes": 0
						}
					}
				]
			},
			{
				"number": "00018",
				"teacher": "Vanessa Gordon",
				"schedule": [
					{
						"day": "Thursday",
						"begin": "10:00 AM",
						"end": "12:00 PM",
						"duration": {
							"hours": 2,
							"minutes": 0
						}
					},
					{
						"day": "Monday",
						"begin": "2:00 PM",
						"end": "4:00 PM",
						"duration": {
							"hours": 2,
							"minutes": 0
						}
					}
				]
			},
			{
				"number": "00019",
				"teacher": "Rubens Lima Moraes",
				"schedule": [
					{
						"day": "Wednesday",
						"begin": "8:00 AM",
						"end": "10:00 AM",
						"duration": {
							"hours": 2,
							"minutes": 0
						}
					},
					{
						"day": "Monday",
						"begin": "8:00 AM",
						"end": "10:00 AM",
						"duration": {
							"hours": 2,
							"minutes": 0
						}
					}
				]
			},
			{
				"number": "00020",
				"teacher": "Francine Small",
				"schedule": [
					{
						"day": "Wednesday",
						"begin": "10:00 AM",
						"end": "12:00 PM",
						"duration": {
							"hours": 2,
							"minutes": 0
						}
					},
					{
						"day": "Monday",
						"begin": "10:00 AM",
						"end": "12:00 PM",
						"duration": {
							"hours": 2,
							"minutes": 0
						}
					}
				]
			},
			{
				"number": "00021",
				"teacher": "Jean Duclos Alegue Feugo",
				"schedule": [
					{
						"day": "Friday",
						"begin": "10:00 AM",
						"end": "12:00 PM",
						"duration": {
							"hours": 2,
							"minutes": 0
						}
					},
					{
						"day": "Tuesday",
						"begin": "10:00 AM",
						"end": "12:00 PM",
						"duration": {
							"hours": 2,
							"minutes": 0
						}
					}
				]
			},
			{
				"number": "00022",
				"teacher": "Jean Duclos Alegue Feugo",
				"schedule": [
					{
						"day": "Thursday",
						"begin": "4:00 PM",
						"end": "6:00 PM",
						"duration": {
							"hours": 2,
							"minutes": 0
						}
					},
					{
						"day": "Tuesday",
						"begin": "4:00 PM",
						"end": "6:00 PM",
						"duration": {
							"hours": 2,
							"minutes": 0
						}
					}
				]
			},
			{
				"number": "00023",
				"teacher": "Marc-André Girouard",
				"schedule": [
					{
						"day": "Friday",
						"begin": "8:00 AM",
						"end": "10:00 AM",
						"duration": {
							"hours": 2,
							"minutes": 0
						}
					},
					{
						"day": "Tuesday",
						"begin": "8:00 AM",
						"end": "10:00 AM",
						"duration": {
							"hours": 2,
							"minutes": 0
						}
					}
				]
			},
			{
				"number": "00024",
				"teacher": "Marc-André Girouard",
				"schedule": [
					{
						"day": "Friday",
						"begin": "12:00 PM",
						"end": "2:00 PM",
						"duration": {
							"hours": 2,
							"minutes": 0
						}
					},
					{
						"day": "Wednesday",
						"begin": "12:00 PM",
						"end": "2:00 PM",
						"duration": {
							"hours": 2,
							"minutes": 0
						}
					}
				]
			},
			{
				"number": "00025",
				"teacher": "Sacha Des Rosiers",
				"schedule": [
					{
						"day": "Friday",
						"begin": "8:00 AM",
						"end": "10:00 AM",
						"duration": {
							"hours": 2,
							"minutes": 0
						}
					},
					{
						"day": "Tuesday",
						"begin": "8:00 AM",
						"end": "10:00 AM",
						"duration": {
							"hours": 2,
							"minutes": 0
						}
					}
				]
			},
			{
				"number": "00026",
				"teacher": "Sacha Des Rosiers",
				"schedule": [
					{
						"day": "Thursday",
						"begin": "8:00 AM",
						"end": "10:00 AM",
						"duration": {
							"hours": 2,
							"minutes": 0
						}
					},
					{
						"day": "Monday",
						"begin": "12:00 PM",
						"end": "2:00 PM",
						"duration": {
							"hours": 2,
							"minutes": 0
						}
					}
				]
			},
			{
				"number": "00027",
				"teacher": "Charles-Albert Ramsay",
				"schedule": [
					{
						"day": "Friday",
						"begin": "12:00 PM",
						"end": "2:00 PM",
						"duration": {
							"hours": 2,
							"minutes": 0
						}
					},
					{
						"day": "Wednesday",
						"begin": "12:00 PM",
						"end": "2:00 PM",
						"duration": {
							"hours": 2,
							"minutes": 0
						}
					}
				]
			},
			{
				"number": "00028",
				"teacher": "Charles-Albert Ramsay",
				"schedule": [
					{
						"day": "Thursday",
						"begin": "2:00 PM",
						"end": "4:00 PM",
						"duration": {
							"hours": 2,
							"minutes": 0
						}
					},
					{
						"day": "Tuesday",
						"begin": "2:00 PM",
						"end": "4:00 PM",
						"duration": {
							"hours": 2,
							"minutes": 0
						}
					}
				]
			},
			{
				"number": "00029",
				"teacher": "Jan Alexandros Arvanitakis",
				"schedule": [
					{
						"day": "Friday",
						"begin": "8:00 AM",
						"end": "10:00 AM",
						"duration": {
							"hours": 2,
							"minutes": 0
						}
					},
					{
						"day": "Tuesday",
						"begin": "8:00 AM",
						"end": "10:00 AM",
						"duration": {
							"hours": 2,
							"minutes": 0
						}
					}
				]
			},
			{
				"number": "00030",
				"teacher": "Julian Nemeth",
				"schedule": [
					{
						"day": "Thursday",
						"begin": "2:00 PM",
						"end": "4:00 PM",
						"duration": {
							"hours": 2,
							"minutes": 0
						}
					},
					{
						"day": "Tuesday",
						"begin": "2:00 PM",
						"end": "4:00 PM",
						"duration": {
							"hours": 2,
							"minutes": 0
						}
					}
				]
			},
			{
				"number": "00031",
				"teacher": "Cynthia De Luca",
				"schedule": [
					{
						"day": "Wednesday",
						"begin": "10:00 AM",
						"end": "12:00 PM",
						"duration": {
							"hours": 2,
							"minutes": 0
						}
					},
					{
						"day": "Monday",
						"begin": "10:00 AM",
						"end": "12:00 PM",
						"duration": {
							"hours": 2,
							"minutes": 0
						}
					}
				]
			},
			{
				"number": "00032",
				"teacher": "Benjamin Lander",
				"schedule": [
					{
						"day": "Thursday",
						"begin": "2:00 PM",
						"end": "4:00 PM",
						"duration": {
							"hours": 2,
							"minutes": 0
						}
					},
					{
						"day": "Tuesday",
						"begin": "2:00 PM",
						"end": "4:00 PM",
						"duration": {
							"hours": 2,
							"minutes": 0
						}
					}
				]
			},
			{
				"number": "00033",
				"teacher": "Mark Beauchamp",
				"schedule": [
					{
						"day": "Thursday",
						"begin": "4:00 PM",
						"end": "6:00 PM",
						"duration": {
							"hours": 2,
							"minutes": 0
						}
					},
					{
						"day": "Tuesday",
						"begin": "4:00 PM",
						"end": "6:00 PM",
						"duration": {
							"hours": 2,
							"minutes": 0
						}
					}
				]
			},
			{
				"number": "00034",
				"teacher": "Maryann Farkas",
				"schedule": [
					{
						"day": "Thursday",
						"begin": "4:00 PM",
						"end": "6:00 PM",
						"duration": {
							"hours": 2,
							"minutes": 0
						}
					},
					{
						"day": "Tuesday",
						"begin": "4:00 PM",
						"end": "6:00 PM",
						"duration": {
							"hours": 2,
							"minutes": 0
						}
					}
				]
			},
			{
				"number": "00035",
				"teacher": "Benjamin Lander",
				"schedule": [
					{
						"day": "Thursday",
						"begin": "12:00 PM",
						"end": "2:00 PM",
						"duration": {
							"hours": 2,
							"minutes": 0
						}
					},
					{
						"day": "Tuesday",
						"begin": "12:00 PM",
						"end": "2:00 PM",
						"duration": {
							"hours": 2,
							"minutes": 0
						}
					}
				]
			},
			{
				"number": "00036",
				"teacher": "Jan Alexandros Arvanitakis",
				"schedule": [
					{
						"day": "Thursday",
						"begin": "10:00 AM",
						"end": "12:00 PM",
						"duration": {
							"hours": 2,
							"minutes": 0
						}
					},
					{
						"day": "Monday",
						"begin": "2:00 PM",
						"end": "4:00 PM",
						"duration": {
							"hours": 2,
							"minutes": 0
						}
					}
				]
			},
			{
				"number": "00037",
				"teacher": "Lisa Steffen",
				"schedule": [
					{
						"day": "Friday",
						"begin": "12:00 PM",
						"end": "2:00 PM",
						"duration": {
							"hours": 2,
							"minutes": 0
						}
					},
					{
						"day": "Wednesday",
						"begin": "12:00 PM",
						"end": "2:00 PM",
						"duration": {
							"hours": 2,
							"minutes": 0
						}
					}
				]
			},
			{
				"number": "00038",
				"teacher": "Ray Claudio Pino",
				"schedule": [
					{
						"day": "Wednesday",
						"begin": "10:00 AM",
						"end": "12:00 PM",
						"duration": {
							"hours": 2,
							"minutes": 0
						}
					},
					{
						"day": "Monday",
						"begin": "10:00 AM",
						"end": "12:00 PM",
						"duration": {
							"hours": 2,
							"minutes": 0
						}
					}
				]
			},
			{
				"number": "00039",
				"teacher": "Sara Louise Kendall",
				"schedule": [
					{
						"day": "Thursday",
						"begin": "10:00 AM",
						"end": "12:00 PM",
						"duration": {
							"hours": 2,
							"minutes": 0
						}
					},
					{
						"day": "Monday",
						"begin": "2:00 PM",
						"end": "4:00 PM",
						"duration": {
							"hours": 2,
							"minutes": 0
						}
					}
				]
			},
			{
				"number": "00040",
				"teacher": "Laurence Nixon",
				"schedule": [
					{
						"day": "Thursday",
						"begin": "10:00 AM",
						"end": "12:00 PM",
						"duration": {
							"hours": 2,
							"minutes": 0
						}
					},
					{
						"day": "Monday",
						"begin": "2:00 PM",
						"end": "4:00 PM",
						"duration": {
							"hours": 2,
							"minutes": 0
						}
					}
				]
			},
			{
				"number": "00041",
				"teacher": "Laurence Nixon",
				"schedule": [
					{
						"day": "Wednesday",
						"begin": "4:00 PM",
						"end": "6:00 PM",
						"duration": {
							"hours": 2,
							"minutes": 0
						}
					},
					{
						"day": "Monday",
						"begin": "4:00 PM",
						"end": "6:00 PM",
						"duration": {
							"hours": 2,
							"minutes": 0
						}
					}
				]
			},
			{
				"number": "00042",
				"teacher": "Rubens Lima Moraes",
				"schedule": [
					{
						"day": "Friday",
						"begin": "8:00 AM",
						"end": "10:00 AM",
						"duration": {
							"hours": 2,
							"minutes": 0
						}
					},
					{
						"day": "Tuesday",
						"begin": "8:00 AM",
						"end": "10:00 AM",
						"duration": {
							"hours": 2,
							"minutes": 0
						}
					}
				]
			},
			{
				"number": "00043",
				"teacher": "Cynthia De Luca",
				"schedule": [
					{
						"day": "Wednesday",
						"begin": "8:00 AM",
						"end": "10:00 AM",
						"duration": {
							"hours": 2,
							"minutes": 0
						}
					},
					{
						"day": "Monday",
						"begin": "8:00 AM",
						"end": "10:00 AM",
						"duration": {
							"hours": 2,
							"minutes": 0
						}
					}
				]
			},
			{
				"number": "00044",
				"teacher": "Carolina Pineda",
				"schedule": [
					{
						"day": "Wednesday",
						"begin": "4:00 PM",
						"end": "6:00 PM",
						"duration": {
							"hours": 2,
							"minutes": 0
						}
					},
					{
						"day": "Monday",
						"begin": "4:00 PM",
						"end": "6:00 PM",
						"duration": {
							"hours": 2,
							"minutes": 0
						}
					}
				]
			},
			{
				"number": "00045",
				"teacher": "Ray Claudio Pino",
				"schedule": [
					{
						"day": "Thursday",
						"begin": "8:00 AM",
						"end": "10:00 AM",
						"duration": {
							"hours": 2,
							"minutes": 0
						}
					},
					{
						"day": "Monday",
						"begin": "12:00 PM",
						"end": "2:00 PM",
						"duration": {
							"hours": 2,
							"minutes": 0
						}
					}
				]
			},
			{
				"number": "00046",
				"teacher": "Ray Claudio Pino",
				"schedule": [
					{
						"day": "Thursday",
						"begin": "4:00 PM",
						"end": "6:00 PM",
						"duration": {
							"hours": 2,
							"minutes": 0
						}
					},
					{
						"day": "Tuesday",
						"begin": "4:00 PM",
						"end": "6:00 PM",
						"duration": {
							"hours": 2,
							"minutes": 0
						}
					}
				]
			}
		]
	}
]